haizelabs/__init__.py
haizelabs/auth.py
haizelabs/client.py
haizelabs/logger/logger.py
haizelabs/logger/types.py
haizelabs/services/__init__.py
haizelabs/services/judges.py
haizelabs/services/testing.py
haizelabs-0.0.4.dist-info/METADATA
haizelabs-0.0.4.dist-info/WHEEL
haizelabs-0.0.4.dist-info/licenses/LICENSE
haizelabs-0.0.4.dist-info/RECORD
