Metadata-Version: 2.3
Name: haizelabs
Version: 0.0.4
Summary: Python library for Haize Labs
Author-email: Haize Labs <contact@haizelabs.com>
License: Apache-2.0
Requires-Python: >=3.9
Requires-Dist: haizelabs-api
Requires-Dist: requests
